keyes/KEyes.py
keyes/__init__.py
keyes/resources.py
keyes-1.0.dist-info/entry_points.txt
keyes-1.0.dist-info/LICENSE
keyes-1.0.dist-info/WHEEL
keyes-1.0.dist-info/METADATA
keyes-1.0.dist-info/RECORD
