Metadata-Version: 2.1
Name: KEyes
Version: 1.0
Summary: Shows the faces of KDE developers with goggly eyes that follow your mouse.
Keywords: KDE,toy,Qt
Author: P. Varet
Requires-Python: >= 3.11
Classifier: Development Status :: 5 - Production/Stable
Classifier: Environment :: X11 Applications :: Qt
Classifier: Intended Audience :: Other Audience
Classifier: License :: OSI Approved :: GNU General Public License v3 (GPLv3)
Classifier: Topic :: Games/Entertainment
Requires-Dist: PySide6>=6.6
Project-URL: Repository, https://github.com/pvaret/keyes.git
